yowsup_celery/__init__.py
yowsup_celery/celery.py
yowsup_celery/exceptions.py
yowsup_celery/layer.py
yowsup_celery/layer_interface.py
yowsup_celery/stack.py
yowsup_celery/steps.py
yowsup_celery/tasks.py
yowsup_celery/utils.py
yowsup_celery-0.2.1.dist-info/DESCRIPTION.rst
yowsup_celery-0.2.1.dist-info/METADATA
yowsup_celery-0.2.1.dist-info/RECORD
yowsup_celery-0.2.1.dist-info/WHEEL
yowsup_celery-0.2.1.dist-info/metadata.json
yowsup_celery-0.2.1.dist-info/top_level.txt
