Metadata-Version: 2.0
Name: yowsup-celery
Version: 0.2.1
Summary: Yowsup integrated in a celery architecture
Home-page: https://github.com/jlmadurga/yowsup-celery
Author: Juan Madurga
Author-email: jlmadurga@gmail.com
License: ISCL
Keywords: yowsup-celery
Platform: UNKNOWN
Classifier: Development Status :: 2 - Pre-Alpha
Classifier: Intended Audience :: Developers
Classifier: License :: OSI Approved :: ISC License (ISCL)
Classifier: Natural Language :: English
Classifier: Programming Language :: Python :: 2
Classifier: Programming Language :: Python :: 2.7
Classifier: Programming Language :: Python :: 3
Classifier: Programming Language :: Python :: 3.3
Classifier: Programming Language :: Python :: 3.4
Requires-Dist: celery (>=3.1.19)
Requires-Dist: gevent (>=1.0.2)
Requires-Dist: yowsup2
